spctl/__init__.py
spctl/helpers.py
spctl/ngspice.py
spctl/optimize.py
spctl/regression.py
spctl/xyce.py
spctl-1.0.1.dist-info/licenses/LICENSE
spctl-1.0.1.dist-info/METADATA
spctl-1.0.1.dist-info/WHEEL
spctl-1.0.1.dist-info/top_level.txt
spctl-1.0.1.dist-info/RECORD
