Metadata-Version: 2.4
Name: spctl
Version: 1.0.1
Summary: Module for controling SPICE simulations
Author: Christoph Weiser
License:                     GNU GENERAL PUBLIC LICENSE
Project-URL: Homepage, https://github.com/christoph-weiser/spctl
Keywords: spice,analysis,control
Classifier: License :: OSI Approved :: GNU General Public License v3 or later (GPLv3+)
Classifier: Programming Language :: Python
Classifier: Programming Language :: Python :: 3
Requires-Python: >=3.9
License-File: LICENSE
Requires-Dist: spatk
Requires-Dist: filelock
Requires-Dist: numpy
Requires-Dist: pandas
Requires-Dist: scipy
Provides-Extra: dev
Requires-Dist: pytest; extra == "dev"
Dynamic: license-file
